sherry/__init__.py
sherry/engine.py
sherry/methods.py
sherry/node.py
sherry/requestcontext.py
sherry/response.py
sherry/router.py
sherry/utils.py
sherry/decorators/__init__.py
sherry/decorators/handler.py
sherry-0.0.6.dist-info/LICENSE
sherry-0.0.6.dist-info/METADATA
sherry-0.0.6.dist-info/WHEEL
sherry-0.0.6.dist-info/top_level.txt
sherry-0.0.6.dist-info/RECORD
