Metadata-Version: 2.1
Name: sherry
Version: 0.0.6
Summary: Python web framework
Maintainer: startracex
License: BSD 2-Clause License
Project-URL: Repository, https://github.com/startracex/sherry
Classifier: Programming Language :: Python :: 3
License-File: LICENSE
